ajaxlogin/__init__.py
ajaxlogin/common.py
ajaxlogin/controllers.py
ajaxlogin/settings.py
ajaxlogin/tools.py
ajaxlogin-0.0.2.dist-info/LICENSE
ajaxlogin-0.0.2.dist-info/METADATA
ajaxlogin-0.0.2.dist-info/WHEEL
ajaxlogin-0.0.2.dist-info/top_level.txt
ajaxlogin-0.0.2.dist-info/RECORD
