Metadata-Version: 2.1
Name: ajaxlogin
Version: 0.0.2
Summary: A lightweight ajax login solution py4web based
Home-page: UNKNOWN
Author: Manuele Pesenti
Author-email: manuele@inventati.org
License: UNKNOWN
Platform: UNKNOWN
Classifier: Programming Language :: Python :: 3
Classifier: License :: OSI Approved :: MIT License
Classifier: Operating System :: OS Independent
Requires-Python: >=3.6
License-File: LICENSE
Requires-Dist: py4web (>=1.20210426.1)
Requires-Dist: mptools (>=1.0.6)
